sagenetgw/__init__.py
sagenetgw/classes.py
sagenetgw/metrics.py
sagenetgw/models.py
sagenetgw/models/best_gw_model_CosmicNet2.pth
sagenetgw/models/best_gw_model_LSTM.pth
sagenetgw/models/best_gw_model_RNN.pth
sagenetgw/models/best_gw_model_Transformer.pth
sagenetgw/stiffGWpy/.git
sagenetgw/stiffGWpy/LCDM_stiff_Neff.py
sagenetgw/stiffGWpy/LICENSE.md
sagenetgw/stiffGWpy/README.md
sagenetgw/stiffGWpy/__init__.py
sagenetgw/stiffGWpy/base_param.yml
sagenetgw/stiffGWpy/benchmark_th.dat
sagenetgw/stiffGWpy/eos2020.dat
sagenetgw/stiffGWpy/functions.py
sagenetgw/stiffGWpy/global_param.py
sagenetgw/stiffGWpy/stiff_SGWB.py
sagenetgw/stiffGWpy/th.dat
sagenetgw/stiffGWpy/cobaya/IPTA_LVK.yaml
sagenetgw/stiffGWpy/cobaya/LVK_Delta_logT.yaml
sagenetgw/stiffGWpy/cobaya/LVK_input.yaml
sagenetgw/stiffGWpy/cobaya/PTA_LVK_BBN.yaml
sagenetgw/stiffGWpy/cobaya/__init.py__
sagenetgw/stiffGWpy/cobaya/alterbbn.py
sagenetgw/stiffGWpy/cobaya/stiffGW.py
sagenetgw/stiffGWpy/cobaya/stiffGW.yaml
sagenetgw/stiffGWpy/cobaya/likelihoods/__init__.py
sagenetgw/stiffGWpy/cobaya/likelihoods/LIGO_SGWB/C_O1_O2_O3.dat
sagenetgw/stiffGWpy/cobaya/likelihoods/LIGO_SGWB/LVK_SGWB_CC.py
sagenetgw/stiffGWpy/cobaya/likelihoods/LIGO_SGWB/LVK_SGWB_CC.yaml
sagenetgw/stiffGWpy/cobaya/likelihoods/LIGO_SGWB/__init__.py
sagenetgw/stiffGWpy/cobaya/likelihoods/PTA/IPTA.py
sagenetgw/stiffGWpy/cobaya/likelihoods/PTA/IPTA.yaml
sagenetgw/stiffGWpy/cobaya/likelihoods/PTA/NANOGrav.py
sagenetgw/stiffGWpy/cobaya/likelihoods/PTA/NANOGrav.yaml
sagenetgw/stiffGWpy/cobaya/likelihoods/PTA/__init__.py
sagenetgw/stiffGWpy/cobaya/likelihoods/PTA/EPTAdr2/EPTA_dr2new.dat
sagenetgw/stiffGWpy/cobaya/likelihoods/PTA/EPTAdr2/EPTA_dr2new_mock.dat
sagenetgw/stiffGWpy/cobaya/likelihoods/PTA/EPTAdr2/freqs_dr2new.txt
sagenetgw/stiffGWpy/cobaya/likelihoods/PTA/EPTAdr2/.ipynb_checkpoints/freqs_dr2new-checkpoint.txt
sagenetgw/stiffGWpy/cobaya/likelihoods/PTA/IPTAdr2/IPTA_dr2_low_H02.dat
sagenetgw-0.1.11.dist-info/METADATA
sagenetgw-0.1.11.dist-info/WHEEL
sagenetgw-0.1.11.dist-info/licenses/LICENSE
sagenetgw-0.1.11.dist-info/RECORD
