Metadata-Version: 2.4
Name: sagenetgw
Version: 0.1.11
Summary: A Python package for gravitational wave analysis using neural networks
Project-URL: Homepage, https://github.com/luoyifang/sagenet
Project-URL: Repository, https://github.com/luoyifang/sagenet
Author-email: Yifang Luo <luoyifang@bupt.cn>
License: MIT License
License-File: LICENSE
Keywords: gravitational waves,machine learning,neural networks
Classifier: License :: OSI Approved :: MIT License
Classifier: Operating System :: OS Independent
Classifier: Programming Language :: Python :: 3
Requires-Python: >=3.8
Requires-Dist: numpy>=1.21.0
Requires-Dist: scikit-learn>=1.6.1
Requires-Dist: torch>=1.9.0
